malla/__init__.py
malla/directed_edge.py
malla/off.py
malla-0.1.7.dist-info/METADATA
malla-0.1.7.dist-info/WHEEL
malla-0.1.7.dist-info/RECORD
