Metadata-Version: 2.1
Name: malla
Version: 0.1.7
Summary: 
Author: Dimas Martínez
Author-email: dimas@ufam.edu.br
Requires-Python: >=3.10,<4.0
Classifier: Programming Language :: Python :: 3
Classifier: Programming Language :: Python :: 3.10
Classifier: Programming Language :: Python :: 3.11
